mxpissh/__init__.py
mxpissh/_version.py
mxpissh/handler.py
mxpissh/main.py
mxpissh/policy.py
mxpissh/settings.py
mxpissh/utils.py
mxpissh/worker.py
mxpissh/static/css/bootstrap.min.css
mxpissh/static/css/fullscreen.min.css
mxpissh/static/css/xterm.min.css
mxpissh/static/css/fonts/.gitignore
mxpissh/static/img/favicon.png
mxpissh/static/js/bootstrap.min.js
mxpissh/static/js/jquery.min.js
mxpissh/static/js/main.js
mxpissh/static/js/popper.min.js
mxpissh/static/js/xterm-addon-fit.min.js
mxpissh/static/js/xterm.min.js
mxpissh/templates/index.html
mxpissh-1.6.2.dist-info/LICENSE
mxpissh-1.6.2.dist-info/METADATA
mxpissh-1.6.2.dist-info/WHEEL
mxpissh-1.6.2.dist-info/entry_points.txt
mxpissh-1.6.2.dist-info/top_level.txt
mxpissh-1.6.2.dist-info/RECORD
