Metadata-Version: 2.1
Name: mxpissh
Version: 1.6.2
Summary: Web based ssh client
Home-page: https://github.com/huashengdun/mxpissh
Author: Shengdun Hua
Author-email: webmaster0115@gmail.com
License: MIT
Platform: UNKNOWN
Classifier: Programming Language :: Python
Classifier: Programming Language :: Python :: 3
Classifier: Programming Language :: Python :: 3.6
Classifier: Programming Language :: Python :: 3.7
Classifier: Programming Language :: Python :: 3.8
Classifier: Programming Language :: Python :: 3.9
Classifier: Programming Language :: Python :: 3.10
Classifier: Programming Language :: Python :: 3.11
Requires-Dist: tornado (>=4.5.0)
Requires-Dist: paramiko (>=2.3.1)
